crau/__init__.py
crau/__main__.py
crau/cli.py
crau/io.py
crau/spider.py
crau/utils.py
crau/version.py
crau-0.3.3.dist-info/LICENSE
crau-0.3.3.dist-info/METADATA
crau-0.3.3.dist-info/WHEEL
crau-0.3.3.dist-info/entry_points.txt
crau-0.3.3.dist-info/top_level.txt
crau-0.3.3.dist-info/RECORD
