Metadata-Version: 2.1
Name: crau
Version: 0.3.3
Summary: Easy-to-use Web archiver
Home-page: https://github.com/turicas/crau/
Author: Álvaro Justen
Author-email: alvarojusten@gmail.com
License: UNKNOWN
Keywords: web crawling scraping archiving
Platform: UNKNOWN
Classifier: License :: OSI Approved :: GNU Lesser General Public License v3 or later (LGPLv3+)
Classifier: Natural Language :: English
Classifier: Operating System :: OS Independent
Classifier: Programming Language :: Python :: 3.7
License-File: LICENSE
Requires-Dist: click
Requires-Dist: pywb
Requires-Dist: scrapy
Requires-Dist: tqdm
Requires-Dist: warcio
